LICENSE
README.md
setup.cfg
setup.py
multitaper/__init__.py
multitaper/mtcross.py
multitaper/mtspec.py
multitaper/utils.py
multitaper.egg-info/PKG-INFO
multitaper.egg-info/SOURCES.txt
multitaper.egg-info/dependency_links.txt
multitaper.egg-info/requires.txt
multitaper.egg-info/top_level.txt
multitaper/examples/mtspec_deconv.ipynb
multitaper/examples/mtspec_dual_freq.ipynb
multitaper/examples/mtspec_src.ipynb
multitaper/examples/mtspec_timefreq.ipynb
multitaper/examples/paper09_fig1_2.py
multitaper/examples/paper09_fig3.py
multitaper/examples/paper09_fig4_5.py
multitaper/examples/paper09_fig6.py
multitaper/examples/paper09_figures.ipynb
multitaper/examples/figures/df_coherence.png
multitaper/examples/figures/df_phase.jpg
multitaper/examples/figures/df_waveforms.png
multitaper/examples/figures/irf_compare.jpg
multitaper/examples/figures/irf_compare.png
multitaper/examples/figures/irf_waveforms.jpg
multitaper/examples/figures/irf_waveforms.png
multitaper/examples/figures/src_stf.png
multitaper/examples/figures/src_waveforms.png
multitaper/examples/figures/tf_spec1.jpg
multitaper/examples/figures/tf_spec1.png
multitaper/examples/figures/tf_spec2.png
multitaper/examples/figures/tf_waveforms.png